nonebot_plugin_cp_broadcast/__init__.py
nonebot_plugin_cp_broadcast/aiosqlite.py
nonebot_plugin_cp_broadcast/atcoder.py
nonebot_plugin_cp_broadcast/codeforces.py
nonebot_plugin_cp_broadcast/config.py
nonebot_plugin_cp_broadcast/nowcoder.py
nonebot_plugin_cp_broadcast/utils.py
nonebot_plugin_cp_broadcast-2.3.2.dist-info/METADATA
nonebot_plugin_cp_broadcast-2.3.2.dist-info/WHEEL
nonebot_plugin_cp_broadcast-2.3.2.dist-info/licenses/LICENSE
nonebot_plugin_cp_broadcast-2.3.2.dist-info/RECORD
