Metadata-Version: 2.4
Name: nonebot-plugin-cp-broadcast
Version: 2.3.2
Summary: Codeforces、牛客、AtCoder平台比赛查询，ACMer 必备
License: MIT
License-File: LICENSE
Author: HuParry
Author-email: hu_parry@qq.com
Requires-Python: >=3.8
Classifier: License :: OSI Approved :: MIT License
Classifier: Programming Language :: Python :: 3
Classifier: Programming Language :: Python :: 3.8
Classifier: Programming Language :: Python :: 3.9
Classifier: Programming Language :: Python :: 3.10
Classifier: Programming Language :: Python :: 3.11
Classifier: Programming Language :: Python :: 3.12
Classifier: Programming Language :: Python :: 3.13
Classifier: Programming Language :: Python :: 3.14
Requires-Dist: aiosqlite (>=0.13.0,<0.14.0)
Requires-Dist: bs4 (>=0.0.1)
Requires-Dist: fake-useragent (>=1.1.3)
Requires-Dist: httpx (>=0.20.0,<1.0.0)
Requires-Dist: nonebot-adapter-onebot (>=2.1.5)
Requires-Dist: nonebot2[fastapi] (>=2.0.0,<3.0.0)
Project-URL: Homepage, https://github.com/HuParry/nonebot-plugin-cp-broadcast
Project-URL: Repository, https://github.com/HuParry/nonebot-plugin-cp-broadcast
